dcaptcha/__init__.py
dcaptcha/__main__.py
DCaptcha-0.0.4.dist-info/LICENSE
DCaptcha-0.0.4.dist-info/METADATA
DCaptcha-0.0.4.dist-info/WHEEL
DCaptcha-0.0.4.dist-info/entry_points.txt
DCaptcha-0.0.4.dist-info/top_level.txt
DCaptcha-0.0.4.dist-info/RECORD
