Metadata-Version: 2.1
Name: DCaptcha
Version: 0.0.4
Summary: Something lol
Home-page: UNKNOWN
Author: devAshton
Author-email: cdnashtonn@gmail.com
License: MIT
Platform: UNKNOWN
Classifier: License :: OSI Approved :: MIT License
Classifier: Programming Language :: Python :: 3.6
Classifier: Programming Language :: Python :: 3.7
Classifier: Programming Language :: Python :: 3.8
License-File: LICENSE
